source_zendesk_talk/__init__.py
source_zendesk_talk/components.py
source_zendesk_talk/manifest.yaml
source_zendesk_talk/run.py
source_zendesk_talk/schemas/account_overview.json
source_zendesk_talk/schemas/addresses.json
source_zendesk_talk/schemas/agents_activity.json
source_zendesk_talk/schemas/agents_overview.json
source_zendesk_talk/schemas/call_legs.json
source_zendesk_talk/schemas/calls.json
source_zendesk_talk/schemas/current_queue_activity.json
source_zendesk_talk/schemas/greeting_categories.json
source_zendesk_talk/schemas/greetings.json
source_zendesk_talk/schemas/ivr_menus.json
source_zendesk_talk/schemas/ivr_routes.json
source_zendesk_talk/schemas/ivrs.json
source_zendesk_talk/schemas/phone_numbers.json
source_zendesk_talk/source.py
airbyte_source_zendesk_talk-1.0.21.dist-info/METADATA
airbyte_source_zendesk_talk-1.0.21.dist-info/WHEEL
airbyte_source_zendesk_talk-1.0.21.dist-info/entry_points.txt
airbyte_source_zendesk_talk-1.0.21.dist-info/RECORD
